devpkg/__init__.py
devpkg/arguer.py
devpkg/colors.py
devpkg/decorators.py
devpkg/deprecate.py
devpkg/is_literal.py
devpkg/platform.py
devpkg/setup.py
devpkg/singleton.py
devpkg/traceback.py
devpkg/versions.py
devpkg-0.2.2.dist-info/LICENSE
devpkg-0.2.2.dist-info/METADATA
devpkg-0.2.2.dist-info/WHEEL
devpkg-0.2.2.dist-info/RECORD
